falco/__init__.py
falco/conf.py
falco/db_routers.py
falco/decorators.py
falco/htmx.py
falco/models.py
falco/pagination.py
falco/py.typed
falco/sentry.py
falco/types.py
falco/urls.py
falco/utils.py
falco/views.py
falco/management/__init__.py
falco/management/base.py
falco/management/commands/__init__.py
falco/management/commands/copy_template.py
falco/management/commands/crud.py
falco/management/commands/htmx.py
falco/management/commands/htmx_ext.py
falco/management/commands/list_templates.py
falco/management/commands/reset_migrations.py
falco/management/commands/rm_migrations.py
falco/management/commands/start_app.py
falco/management/commands/work.py
falco/templates/crud/detail.html
falco/templates/crud/form.html
falco/templates/crud/forms.py.dtl
falco/templates/crud/list.html
falco/templates/crud/views.py.dtl
falco/templates/partials/pagination.html
falco/templates/partials/table.html
falco/templatetags/__init__.py
falco/templatetags/falco.py
falco_app-0.3.8.dist-info/METADATA
falco_app-0.3.8.dist-info/WHEEL
falco_app-0.3.8.dist-info/licenses/LICENSE.txt
falco_app-0.3.8.dist-info/RECORD
