Metadata-Version: 2.4
Name: falco-app
Version: 0.3.8
Summary: Falco is a toolkit to build web apps with django faster.
Project-URL: Documentation, https://github.com/falcopackages/falco#readme
Project-URL: Issues, https://github.com/falcopackages/falco/issues
Project-URL: Source, https://github.com/falcopackages/falco
Author-email: Tobi DEGNON <tobidegnon@proton.me>
License-File: LICENSE.txt
Keywords: cookiecutter,django,project-template,python
Classifier: Development Status :: 4 - Beta
Classifier: Framework :: Django :: 4
Classifier: Framework :: Django :: 4.0
Classifier: Framework :: Django :: 4.1
Classifier: Framework :: Django :: 4.2
Classifier: Framework :: Django :: 5.0
Classifier: Intended Audience :: Developers
Classifier: Natural Language :: English
Classifier: Programming Language :: Python
Classifier: Programming Language :: Python :: 3 :: Only
Classifier: Programming Language :: Python :: 3.10
Classifier: Programming Language :: Python :: 3.11
Classifier: Programming Language :: Python :: 3.12
Classifier: Programming Language :: Python :: 3.13
Classifier: Programming Language :: Python :: Implementation :: CPython
Classifier: Programming Language :: Python :: Implementation :: PyPy
Requires-Python: >=3.10
Requires-Dist: django
Requires-Dist: httpx
Requires-Dist: parso
Requires-Dist: rich
